agentsdk_gemini_adapter/__init__.py
agentsdk_gemini_adapter/config.py
agentsdk_gemini_adapter-0.1.0.dist-info/licenses/LICENSE
agentsdk_gemini_adapter-0.1.0.dist-info/METADATA
agentsdk_gemini_adapter-0.1.0.dist-info/WHEEL
agentsdk_gemini_adapter-0.1.0.dist-info/top_level.txt
agentsdk_gemini_adapter-0.1.0.dist-info/RECORD
