Metadata-Version: 2.4
Name: agentsdk-gemini-adapter
Version: 0.1.0
Summary: A Python adapter for using Google Gemini with OpenAI Agents SDK
Author-email: Abbas Asad <abbas07tech@gmail.com>
Maintainer-email: Abbas Asad <abbas07tech@gmail.com>
License: MIT
Keywords: gemini,openai,agents,ai,machine-learning
Classifier: Development Status :: 3 - Alpha
Classifier: Intended Audience :: Developers
Classifier: License :: OSI Approved :: MIT License
Classifier: Operating System :: OS Independent
Classifier: Programming Language :: Python :: 3
Classifier: Programming Language :: Python :: 3.7
Classifier: Programming Language :: Python :: 3.8
Classifier: Programming Language :: Python :: 3.9
Classifier: Programming Language :: Python :: 3.10
Classifier: Programming Language :: Python :: 3.11
Classifier: Programming Language :: Python :: 3.12
Requires-Python: >=3.7
License-File: LICENSE
Dynamic: license-file
